pelican/plugins/htmlmin/__init__.py
pelican/plugins/htmlmin/minify.py
pelican_htmlmin-2.0.0.dist-info/METADATA
pelican_htmlmin-2.0.0.dist-info/WHEEL
pelican_htmlmin-2.0.0.dist-info/top_level.txt
pelican_htmlmin-2.0.0.dist-info/RECORD
