Metadata-Version: 2.1
Name: pelican-htmlmin
Version: 2.0.0
Summary: Minifies HTML files generated by Pelican
Home-page: https://git.bryanbrattlof.com/pelican-htmlmin
Author: Bryan Brattlof
Author-email: hello@bryanbrattlof.com
License: MIT
Platform: UNKNOWN
Classifier: Development Status :: 5 - Production/Stable
Classifier: Intended Audience :: Developers
Classifier: Topic :: Software Development :: Libraries
Classifier: Framework :: Pelican
Classifier: Framework :: Pelican :: Plugins
Classifier: License :: OSI Approved :: MIT License
Classifier: Programming Language :: Python
Classifier: Programming Language :: Python :: 3
Classifier: Programming Language :: Python :: 3.3
Classifier: Programming Language :: Python :: 3.4
Classifier: Programming Language :: Python :: 3.5
Classifier: Programming Language :: Python :: 3.6
Classifier: Programming Language :: Python :: 3.7
Classifier: Programming Language :: Python :: 3.8
Classifier: Natural Language :: English
Requires-Dist: pelican
Requires-Dist: htmlmin
